{
  "date": "2026-04-22",
  "source_url": "https://www.yalla1shoot.com/matches-today_5/",
  "matches": [
    {
      "id": "النصر-الأهليالقطر-2026-04-22",
      "home": "النصر",
      "away": "الأهلي القطري",
      "home_logo": "https://i0.wp.com/www.yalla1shoot.com/wp-content/uploads/2026/04/7549-logo.png",
      "away_logo": "https://i0.wp.com/www.yalla1shoot.com/wp-content/uploads/2026/04/7085-logo-1.png",
      "time_baghdad": "07:00",
      "status": "NS",
      "status_text": "لم تبدأ بعد",
      "result_text": "",
      "channel": "غير معروف",
      "commentator": "غير معروف",
      "competition": "آسيا, دوري أبطال آسيا 2 - نصف النهائي",
      "match_url": "https://www.yalla1shoot.com/matches/victory-vs-al-ahly-qatar/",
      "_source": "yalla1shoot"
    },
    {
      "id": "أولمبيكآسفي-نهضةالزمامر-2026-04-22",
      "home": "أولمبيك آسفي",
      "away": "نهضة الزمامرة",
      "home_logo": "https://i0.wp.com/www.yalla1shoot.com/wp-content/uploads/2026/04/8210-logo.png",
      "away_logo": "https://i0.wp.com/www.yalla1shoot.com/wp-content/uploads/2026/04/49266-logo.png",
      "time_baghdad": "08:00",
      "status": "NS",
      "status_text": "لم تبدأ بعد",
      "result_text": "",
      "channel": "غير معروف",
      "commentator": "غير معروف",
      "competition": "المغرب, الدوري المغربي",
      "match_url": "https://www.yalla1shoot.com/matches/olympic-safi-vs-renaissance-of-zammara/",
      "_source": "yalla1shoot"
    },
    {
      "id": "إلتشي-أتلتيكومدري-2026-04-22",
      "home": "إلتشي",
      "away": "أتلتيكو مدريد",
      "home_logo": "https://i0.wp.com/www.yalla1shoot.com/wp-content/uploads/2026/04/156-logo.png",
      "away_logo": "https://i0.wp.com/www.yalla1shoot.com/wp-content/uploads/2026/04/134-logo-1.png",
      "time_baghdad": "08:00",
      "status": "NS",
      "status_text": "لم تبدأ بعد",
      "result_text": "",
      "channel": "beIN Sports 6 HD",
      "commentator": "غير معروف",
      "competition": "إسبانيا, الدوري الإسباني",
      "match_url": "https://www.yalla1shoot.com/matches/elche-vs-atletico-madrid/",
      "_source": "yalla1shoot"
    },
    {
      "id": "باريسسانجي-نانت-2026-04-22",
      "home": "باريس سان جيرمان",
      "away": "نانت",
      "home_logo": "https://i0.wp.com/www.yalla1shoot.com/wp-content/uploads/2026/04/480-logo.png",
      "away_logo": "https://i0.wp.com/www.yalla1shoot.com/wp-content/uploads/2026/04/486-logo-150x150.png",
      "time_baghdad": "08:00",
      "status": "NS",
      "status_text": "لم تبدأ بعد",
      "result_text": "",
      "channel": "beIN SPORTS HD 1",
      "commentator": "غير معروف",
      "competition": "فرنسا, الدوري الفرنسي",
      "match_url": "https://www.yalla1shoot.com/matches/paris-saint-germain-vs-nantes/",
      "_source": "yalla1shoot"
    },
    {
      "id": "ريالسوسيداد-خيتافي-2026-04-22",
      "home": "ريال سوسيداد",
      "away": "خيتافي",
      "home_logo": "https://i0.wp.com/www.yalla1shoot.com/wp-content/uploads/2026/04/154-logo.png",
      "away_logo": "https://i0.wp.com/www.yalla1shoot.com/wp-content/uploads/2026/04/140-logo-1.png",
      "time_baghdad": "09:00",
      "status": "NS",
      "status_text": "لم تبدأ بعد",
      "result_text": "",
      "channel": "beIN Sport 8 HD",
      "commentator": "غير معروف",
      "competition": "إسبانيا, الدوري الإسباني",
      "match_url": "https://www.yalla1shoot.com/matches/real-sociedad-vs-getafe/",
      "_source": "yalla1shoot"
    },
    {
      "id": "بايرليفركوز-بايرنميونخ-2026-04-22",
      "home": "باير ليفركوزن",
      "away": "بايرن ميونخ",
      "home_logo": "https://i0.wp.com/www.yalla1shoot.com/wp-content/uploads/2026/04/24129-logo.png",
      "away_logo": "https://i0.wp.com/www.yalla1shoot.com/wp-content/uploads/2026/04/331-logo-150x150.png",
      "time_baghdad": "09:45",
      "status": "NS",
      "status_text": "لم تبدأ بعد",
      "result_text": "",
      "channel": "غير معروف",
      "commentator": "غير معروف",
      "competition": "ألمانيا, كأس المانيا - نصف النهائي",
      "match_url": "https://www.yalla1shoot.com/matches/bayer-leverkusen-vs-bayern-munich/",
      "_source": "yalla1shoot"
    },
    {
      "id": "ستراسبورج-نيس-2026-04-22",
      "home": "ستراسبورج",
      "away": "نيس",
      "home_logo": "https://i0.wp.com/www.yalla1shoot.com/wp-content/uploads/2026/04/479-logo.png",
      "away_logo": "https://i0.wp.com/www.yalla1shoot.com/wp-content/uploads/2026/04/470-logo.png",
      "time_baghdad": "10:00",
      "status": "NS",
      "status_text": "لم تبدأ بعد",
      "result_text": "",
      "channel": "غير معروف",
      "commentator": "غير معروف",
      "competition": "فرنسا, كأس فرنسا - نصف النهائي",
      "match_url": "https://www.yalla1shoot.com/matches/strasbourg-vs-nice/",
      "_source": "yalla1shoot"
    },
    {
      "id": "بورنموث-ليدزيونايتد-2026-04-22",
      "home": "بورنموث",
      "away": "ليدز يونايتد",
      "home_logo": "https://i0.wp.com/www.yalla1shoot.com/wp-content/uploads/2026/04/50-logo.png",
      "away_logo": "https://i0.wp.com/www.yalla1shoot.com/wp-content/uploads/2026/04/36-logo.png",
      "time_baghdad": "10:00",
      "status": "NS",
      "status_text": "لم تبدأ بعد",
      "result_text": "",
      "channel": "beIN SPORTS HD 4",
      "commentator": "غير معروف",
      "competition": "إنجلترا, الدوري الإنجليزي",
      "match_url": "https://www.yalla1shoot.com/matches/bournemouth-vs-leeds-united/",
      "_source": "yalla1shoot"
    },
    {
      "id": "بيرنلي-مانشسترسيتي-2026-04-22",
      "home": "بيرنلي",
      "away": "مانشستر سيتي",
      "home_logo": "https://i0.wp.com/www.yalla1shoot.com/wp-content/uploads/2026/04/12-logo.png",
      "away_logo": "https://i0.wp.com/www.yalla1shoot.com/wp-content/uploads/2026/04/110-logo.png",
      "time_baghdad": "10:00",
      "status": "NS",
      "status_text": "لم تبدأ بعد",
      "result_text": "",
      "channel": "beIN Sports 3 HD",
      "commentator": "غير معروف",
      "competition": "إنجلترا, الدوري الإنجليزي",
      "match_url": "https://www.yalla1shoot.com/matches/burnley-vs-manchester-city/",
      "_source": "yalla1shoot"
    },
    {
      "id": "أتالانتا-لاتسيو-2026-04-22",
      "home": "أتالانتا",
      "away": "لاتسيو",
      "home_logo": "https://i0.wp.com/www.yalla1shoot.com/wp-content/uploads/2026/04/232-logo.png",
      "away_logo": "https://i0.wp.com/www.yalla1shoot.com/wp-content/uploads/2026/04/236-logo.png",
      "time_baghdad": "10:00",
      "status": "NS",
      "status_text": "لم تبدأ بعد",
      "result_text": "",
      "channel": "شاهد - Shahid VIP",
      "commentator": "غير معروف",
      "competition": "إيطاليا, كأس إيطاليا - نصف النهائي",
      "match_url": "https://www.yalla1shoot.com/matches/atalanta-vs-lazio/",
      "_source": "yalla1shoot"
    },
    {
      "id": "الجيشالملكي-نهضةبركان-2026-04-22",
      "home": "الجيش الملكي",
      "away": "نهضة بركان",
      "home_logo": "https://i0.wp.com/www.yalla1shoot.com/wp-content/uploads/2026/04/5455-logo.png",
      "away_logo": "https://i0.wp.com/www.yalla1shoot.com/wp-content/uploads/2026/04/9974-logo-150x150.png",
      "time_baghdad": "10:00",
      "status": "NS",
      "status_text": "لم تبدأ بعد",
      "result_text": "",
      "channel": "الرياضية المغربية (3)",
      "commentator": "غير معروف",
      "competition": "المغرب, الدوري المغربي",
      "match_url": "https://www.yalla1shoot.com/matches/royal-army-vs-berkane-renaissance/",
      "_source": "yalla1shoot"
    },
    {
      "id": "برشلونة-سيلتافيجو-2026-04-22",
      "home": "برشلونة",
      "away": "سيلتا فيجو",
      "home_logo": "https://i0.wp.com/www.yalla1shoot.com/wp-content/uploads/2026/04/132-logo-1.png",
      "away_logo": "https://i0.wp.com/www.yalla1shoot.com/wp-content/uploads/2026/04/158-logo.png",
      "time_baghdad": "10:30",
      "status": "NS",
      "status_text": "لم تبدأ بعد",
      "result_text": "",
      "channel": "beIN SPORTS HD 1",
      "commentator": "غير معروف",
      "competition": "إسبانيا, الدوري الإسباني",
      "match_url": "https://www.yalla1shoot.com/matches/barcelona-vs-celta-vigo/",
      "_source": "yalla1shoot"
    }
  ]
}