{
  "date": "2025-11-30",
  "source_url": "https://www.yalla-shoot.info/matches-today/",
  "matches": [
    {
      "id": "ليتشي-تورينو-2025-11-30",
      "home": "ليتشي",
      "away": "تورينو",
      "home_logo": "https://www.yalla-shoot.info/wp-content/uploads/2025/01/204.png",
      "away_logo": "https://www.yalla-shoot.info/wp-content/uploads/2025/01/144.png",
      "time_baghdad": "13:30",
      "status": "NS",
      "status_text": "لم تبدأ بعد",
      "result_text": "0-0",
      "channel": "Starzplay",
      "commentator": "غير معروف",
      "competition": "إيطاليا, الدوري الإيطالي",
      "_source": "yalla1shoot"
    },
    {
      "id": "كريستالبالا-مانشستريونا-2025-11-30",
      "home": "كريستال بالاس",
      "away": "مانشستر يونايتد",
      "home_logo": "https://www.yalla-shoot.info/wp-content/uploads/2025/02/299.png",
      "away_logo": "https://www.yalla-shoot.info/wp-content/uploads/2025/01/95.png",
      "time_baghdad": "14:00",
      "status": "NS",
      "status_text": "لم تبدأ بعد",
      "result_text": "0-0",
      "channel": "beIN SPORTS HD 1",
      "commentator": "غير معروف",
      "competition": "إنجلترا, الدوري الإنجليزي",
      "_source": "yalla1shoot"
    },
    {
      "id": "فاركو-تليفوناتبني-2025-11-30",
      "home": "فاركو",
      "away": "تليفونات بني سويف",
      "home_logo": "https://www.yalla-shoot.info/wp-content/uploads/2025/01/1880.png",
      "away_logo": "https://www.newyalla-shoot.com/wp-content/uploads/2025/11/8609.png",
      "time_baghdad": "14:30",
      "status": "NS",
      "status_text": "لم تبدأ بعد",
      "result_text": "0-0",
      "channel": "أون سبورت 2",
      "commentator": "غير معروف",
      "competition": "مصر, كأس مصر - دور الـ 32",
      "_source": "yalla1shoot"
    },
    {
      "id": "سانتإيلويل-الهلالالسود-2025-11-30",
      "home": "سانت إيلوي لوبوبو",
      "away": "الهلال السوداني",
      "home_logo": "https://www.yallashootkora.com/wp-content/uploads/2025/11/29705.png",
      "away_logo": "https://www.yalla-shoot.info/wp-content/uploads/2025/09/12778.png",
      "time_baghdad": "15:00",
      "status": "NS",
      "status_text": "لم تبدأ بعد",
      "result_text": "0-0",
      "channel": "beIN Sports 6 HD",
      "commentator": "غير معروف",
      "competition": "أفريقيا, دوري أبطال أفريقيا - المجموعات",
      "_source": "yalla1shoot"
    },
    {
      "id": "ريالسوسيداد-فياريال-2025-11-30",
      "home": "ريال سوسيداد",
      "away": "فياريال",
      "home_logo": "https://www.yalla-shoot.info/wp-content/uploads/2025/01/124.png",
      "away_logo": "https://www.yalla-shoot.info/wp-content/uploads/2025/01/127.png",
      "time_baghdad": "15:00",
      "status": "NS",
      "status_text": "لم تبدأ بعد",
      "result_text": "0-0",
      "channel": "beIN Sports 5 HD",
      "commentator": "غير معروف",
      "competition": "إسبانيا, الدوري الإسباني",
      "_source": "yalla1shoot"
    },
    {
      "id": "ستراسبورج-بريست-2025-11-30",
      "home": "ستراسبورج",
      "away": "بريست",
      "home_logo": "https://www.yalla-shoot.info/wp-content/uploads/2025/02/300.png",
      "away_logo": "https://www.yalla-shoot.info/wp-content/uploads/2025/08/534.png",
      "time_baghdad": "16:00",
      "status": "NS",
      "status_text": "لم تبدأ بعد",
      "result_text": "0-0",
      "channel": "غير معروف",
      "commentator": "غير معروف",
      "competition": "فرنسا, الدوري الفرنسي",
      "_source": "yalla1shoot"
    },
    {
      "id": "بيسا-إنترميلان-2025-11-30",
      "home": "بيسا",
      "away": "إنتر ميلان",
      "home_logo": "https://www.yalla-shoot.info/wp-content/uploads/2025/08/248.png",
      "away_logo": "https://www.yalla-shoot.info/wp-content/uploads/2025/06/224.png",
      "time_baghdad": "16:00",
      "status": "NS",
      "status_text": "لم تبدأ بعد",
      "result_text": "0-0",
      "channel": "Starzplay",
      "commentator": "غير معروف",
      "competition": "إيطاليا, الدوري الإيطالي",
      "_source": "yalla1shoot"
    },
    {
      "id": "وستهاميونا-ليفربول-2025-11-30",
      "home": "وست هام يونايتد",
      "away": "ليفربول",
      "home_logo": "https://www.yalla-shoot.info/wp-content/uploads/2025/02/103.png",
      "away_logo": "https://www.yalla-shoot.info/wp-content/uploads/2025/01/93.png",
      "time_baghdad": "16:05",
      "status": "NS",
      "status_text": "لم تبدأ بعد",
      "result_text": "0-0",
      "channel": "beIN SPORTS HD 1",
      "commentator": "غير معروف",
      "competition": "إنجلترا, الدوري الإنجليزي",
      "_source": "yalla1shoot"
    },
    {
      "id": "نوتنجهامفور-برايتون-2025-11-30",
      "home": "نوتنجهام فورست",
      "away": "برايتون",
      "home_logo": "https://www.yalla-shoot.info/wp-content/uploads/2025/08/29.png",
      "away_logo": "https://www.yalla-shoot.info/wp-content/uploads/2025/01/1426.png",
      "time_baghdad": "16:05",
      "status": "NS",
      "status_text": "لم تبدأ بعد",
      "result_text": "0-0",
      "channel": "غير معروف",
      "commentator": "غير معروف",
      "competition": "إنجلترا, الدوري الإنجليزي",
      "_source": "yalla1shoot"
    },
    {
      "id": "أستونفيلا-وولفرهامبتون-2025-11-30",
      "home": "أستون فيلا",
      "away": "وولفرهامبتون",
      "home_logo": "https://www.yalla-shoot.info/wp-content/uploads/2025/01/84.png",
      "away_logo": "https://www.yalla-shoot.info/wp-content/uploads/2025/08/15.png",
      "time_baghdad": "16:05",
      "status": "NS",
      "status_text": "لم تبدأ بعد",
      "result_text": "0-0",
      "channel": "غير معروف",
      "commentator": "غير معروف",
      "competition": "إنجلترا, الدوري الإنجليزي",
      "_source": "yalla1shoot"
    },
    {
      "id": "إنبي-المقاولونال-2025-11-30",
      "home": "إنبي",
      "away": "المقاولون العرب",
      "home_logo": "https://www.yalla-shoot.info/wp-content/uploads/2025/08/8300.png",
      "away_logo": "https://www.yalla-shoot.info/wp-content/uploads/2025/08/8310.png",
      "time_baghdad": "17:00",
      "status": "NS",
      "status_text": "لم تبدأ بعد",
      "result_text": "0-0",
      "channel": "أون سبورت 1",
      "commentator": "غير معروف",
      "competition": "مصر, كأس مصر - دور الـ 32",
      "_source": "yalla1shoot"
    },
    {
      "id": "إشبيلية-ريالبيتيس-2025-11-30",
      "home": "إشبيلية",
      "away": "ريال بيتيس",
      "home_logo": "https://www.yalla-shoot.info/wp-content/uploads/2025/01/126.png",
      "away_logo": "https://www.yalla-shoot.info/wp-content/uploads/2025/02/123.png",
      "time_baghdad": "17:15",
      "status": "NS",
      "status_text": "لم تبدأ بعد",
      "result_text": "0-0",
      "channel": "beIN Sports 5 HD",
      "commentator": "غير معروف",
      "competition": "إسبانيا, الدوري الإسباني",
      "_source": "yalla1shoot"
    },
    {
      "id": "لوآفر-ليل-2025-11-30",
      "home": "لو آفر",
      "away": "ليل",
      "home_logo": "https://www.yalla-shoot.info/wp-content/uploads/2025/08/485.png",
      "away_logo": "https://www.yalla-shoot.info/wp-content/uploads/2025/01/310.png",
      "time_baghdad": "18:15",
      "status": "NS",
      "status_text": "لم تبدأ بعد",
      "result_text": "0-0",
      "channel": "غير معروف",
      "commentator": "غير معروف",
      "competition": "فرنسا, الدوري الفرنسي",
      "_source": "yalla1shoot"
    },
    {
      "id": "لوريان-نيس-2025-11-30",
      "home": "لوريان",
      "away": "نيس",
      "home_logo": "https://www.yalla-shoot.info/wp-content/uploads/2025/08/472-1.png",
      "away_logo": "https://www.yalla-shoot.info/wp-content/uploads/2025/01/251.png",
      "time_baghdad": "18:15",
      "status": "NS",
      "status_text": "لم تبدأ بعد",
      "result_text": "0-0",
      "channel": "غير معروف",
      "commentator": "غير معروف",
      "competition": "فرنسا, الدوري الفرنسي",
      "_source": "yalla1shoot"
    },
    {
      "id": "أنجيه-لانس-2025-11-30",
      "home": "أنجيه",
      "away": "لانس",
      "home_logo": "https://www.yalla-shoot.info/wp-content/uploads/2025/02/1542.png",
      "away_logo": "https://www.yalla-shoot.info/wp-content/uploads/2025/01/309.png",
      "time_baghdad": "18:15",
      "status": "NS",
      "status_text": "لم تبدأ بعد",
      "result_text": "0-0",
      "channel": "غير معروف",
      "commentator": "غير معروف",
      "competition": "فرنسا, الدوري الفرنسي",
      "_source": "yalla1shoot"
    },
    {
      "id": "تشيلسي-أرسنال-2025-11-30",
      "home": "تشيلسي",
      "away": "أرسنال",
      "home_logo": "https://www.yalla-shoot.info/wp-content/uploads/2025/02/89.png",
      "away_logo": "https://www.yalla-shoot.info/wp-content/uploads/2025/02/83.png",
      "time_baghdad": "18:30",
      "status": "NS",
      "status_text": "لم تبدأ بعد",
      "result_text": "0-0",
      "channel": "غير معروف",
      "commentator": "غير معروف",
      "competition": "إنجلترا, الدوري الإنجليزي",
      "_source": "yalla1shoot"
    },
    {
      "id": "أتالانتا-فيورنتينا-2025-11-30",
      "home": "أتالانتا",
      "away": "فيورنتينا",
      "home_logo": "https://www.yalla-shoot.info/wp-content/uploads/2025/01/128.png",
      "away_logo": "https://www.yalla-shoot.info/wp-content/uploads/2025/02/323.png",
      "time_baghdad": "19:00",
      "status": "NS",
      "status_text": "لم تبدأ بعد",
      "result_text": "0-0",
      "channel": "Starzplay",
      "commentator": "غير معروف",
      "competition": "إيطاليا, الدوري الإيطالي",
      "_source": "yalla1shoot"
    },
    {
      "id": "سيلتافيجو-إسبانيول-2025-11-30",
      "home": "سيلتا فيجو",
      "away": "إسبانيول",
      "home_logo": "https://www.yalla-shoot.info/wp-content/uploads/2025/02/117.png",
      "away_logo": "https://www.yalla-shoot.info/wp-content/uploads/2025/01/119.png",
      "time_baghdad": "19:30",
      "status": "NS",
      "status_text": "لم تبدأ بعد",
      "result_text": "0-0",
      "channel": "beIN Sports 5 HD",
      "commentator": "غير معروف",
      "competition": "إسبانيا, الدوري الإسباني",
      "_source": "yalla1shoot"
    },
    {
      "id": "روما-نابولي-2025-11-30",
      "home": "روما",
      "away": "نابولي",
      "home_logo": "https://www.yalla-shoot.info/wp-content/uploads/2025/01/143.png",
      "away_logo": "https://www.yalla-shoot.info/wp-content/uploads/2025/02/757.png",
      "time_baghdad": "21:45",
      "status": "NS",
      "status_text": "لم تبدأ بعد",
      "result_text": "0-0",
      "channel": "Starzplay",
      "commentator": "غير معروف",
      "competition": "إيطاليا, الدوري الإيطالي",
      "_source": "yalla1shoot"
    },
    {
      "id": "أولمبيكليون-نانت-2025-11-30",
      "home": "أولمبيك ليون",
      "away": "نانت",
      "home_logo": "https://www.yalla-shoot.info/wp-content/uploads/2025/01/211.png",
      "away_logo": "https://www.yalla-shoot.info/wp-content/uploads/2025/02/244.png",
      "time_baghdad": "21:45",
      "status": "NS",
      "status_text": "لم تبدأ بعد",
      "result_text": "0-0",
      "channel": "غير معروف",
      "commentator": "غير معروف",
      "competition": "فرنسا, الدوري الفرنسي",
      "_source": "yalla1shoot"
    },
    {
      "id": "جيرونا-ريالمدريد-2025-11-30",
      "home": "جيرونا",
      "away": "ريال مدريد",
      "home_logo": "https://www.yalla-shoot.info/wp-content/uploads/2025/02/2014.png",
      "away_logo": "https://www.yalla-shoot.info/wp-content/uploads/2025/01/110.png",
      "time_baghdad": "22:00",
      "status": "NS",
      "status_text": "لم تبدأ بعد",
      "result_text": "0-0",
      "channel": "غير معروف",
      "commentator": "غير معروف",
      "competition": "إسبانيا, الدوري الإسباني",
      "_source": "yalla1shoot"
    },
    {
      "id": "إنترميامي-نيوركسيتي-2025-11-30",
      "home": "إنتر ميامي",
      "away": "نيورك سيتي",
      "home_logo": "https://www.yallashootkora.com/wp-content/uploads/2025/11/12790.png",
      "away_logo": "https://www.newyalla-shoot.com/wp-content/uploads/2025/11/UIpR4.png",
      "time_baghdad": "02:00",
      "status": "FT",
      "status_text": "انتهت",
      "result_text": "0-0",
      "channel": "غير معروف",
      "commentator": "غير معروف",
      "competition": "غير معروف",
      "_source": "yalla1shoot"
    }
  ]
}