{
  "date": "2025-09-27",
  "source_url": "https://www.yalla-shoot.info/matches-today/",
  "matches": [
    {
      "id": "برينتفورد-مانشستريونا-2025-09-27",
      "home": "برينتفورد",
      "away": "مانشستر يونايتد",
      "home_logo": "https://www.yalla-shoot.info/wp-content/uploads/2025/02/1920.png",
      "away_logo": "https://www.yalla-shoot.info/wp-content/uploads/2025/01/95.png",
      "time_baghdad": "14:30",
      "status": "NS",
      "status_text": "جارية الان",
      "result_text": "0-0",
      "channel": "beIN SPORTS HD 1",
      "commentator": "غير معروف",
      "competition": "إنجلترا, الدوري الإنجليزي",
      "_source": "yalla1shoot"
    },
    {
      "id": "خيتافي-ليفانتي-2025-09-27",
      "home": "خيتافي",
      "away": "ليفانتي",
      "home_logo": "https://www.yalla-shoot.info/wp-content/uploads/2025/01/317.png",
      "away_logo": "https://www.yalla-shoot.info/wp-content/uploads/2025/08/150.png",
      "time_baghdad": "15:00",
      "status": "NS",
      "status_text": "جارية الان",
      "result_text": "0-0",
      "channel": "beIN SPORTS HD 4",
      "commentator": "غير معروف",
      "competition": "إسبانيا, الدوري الإسباني",
      "_source": "yalla1shoot"
    },
    {
      "id": "كومو-كريمونيسي-2025-09-27",
      "home": "كومو",
      "away": "كريمونيسي",
      "home_logo": "https://www.yalla-shoot.info/wp-content/uploads/2025/01/132.png",
      "away_logo": "https://www.yalla-shoot.info/wp-content/uploads/2025/08/290.png",
      "time_baghdad": "16:00",
      "status": "NS",
      "status_text": "جارية الان",
      "result_text": "0-0",
      "channel": "Starzplay",
      "commentator": "غير معروف",
      "competition": "إيطاليا, الدوري الإيطالي",
      "_source": "yalla1shoot"
    },
    {
      "id": "سانتباولي-بايرليفركوز-2025-09-27",
      "home": "سانت باولي",
      "away": "باير ليفركوزن",
      "home_logo": "https://www.yalla-shoot.info/wp-content/uploads/2025/01/1042.png",
      "away_logo": "https://www.yalla-shoot.info/wp-content/uploads/2025/02/156.png",
      "time_baghdad": "16:30",
      "status": "NS",
      "status_text": "بعد قليل",
      "result_text": "0-0",
      "channel": "شاهد - Shahid VIP",
      "commentator": "غير معروف",
      "competition": "ألمانيا, الدوري الألماني",
      "_source": "yalla1shoot"
    },
    {
      "id": "ماينز05-بوروسيادورت-2025-09-27",
      "home": "ماينز 05",
      "away": "بوروسيا دورتموند",
      "home_logo": "https://www.yalla-shoot.info/wp-content/uploads/2025/01/297.png",
      "away_logo": "https://www.yalla-shoot.info/wp-content/uploads/2025/01/154.png",
      "time_baghdad": "16:30",
      "status": "NS",
      "status_text": "بعد قليل",
      "result_text": "0-0",
      "channel": "شاهد - Shahid VIP",
      "commentator": "غير معروف",
      "competition": "ألمانيا, الدوري الألماني",
      "_source": "yalla1shoot"
    },
    {
      "id": "كريستالبالا-ليفربول-2025-09-27",
      "home": "كريستال بالاس",
      "away": "ليفربول",
      "home_logo": "https://www.yalla-shoot.info/wp-content/uploads/2025/02/299.png",
      "away_logo": "https://www.yalla-shoot.info/wp-content/uploads/2025/01/93.png",
      "time_baghdad": "17:00",
      "status": "NS",
      "status_text": "لم تبدأ بعد",
      "result_text": "0-0",
      "channel": "beIN Sports 3 HD",
      "commentator": "غير معروف",
      "competition": "إنجلترا, الدوري الإنجليزي",
      "_source": "yalla1shoot"
    },
    {
      "id": "مانشسترسيتي-بيرنلي-2025-09-27",
      "home": "مانشستر سيتي",
      "away": "بيرنلي",
      "home_logo": "https://www.yalla-shoot.info/wp-content/uploads/2025/02/94.png",
      "away_logo": "https://www.yalla-shoot.info/wp-content/uploads/2025/08/12.png",
      "time_baghdad": "17:00",
      "status": "NS",
      "status_text": "لم تبدأ بعد",
      "result_text": "0-0",
      "channel": "Bein Sports HD2",
      "commentator": "غير معروف",
      "competition": "إنجلترا, الدوري الإنجليزي",
      "_source": "yalla1shoot"
    },
    {
      "id": "تشيلسي-برايتون-2025-09-27",
      "home": "تشيلسي",
      "away": "برايتون",
      "home_logo": "https://www.yalla-shoot.info/wp-content/uploads/2025/02/89.png",
      "away_logo": "https://www.yalla-shoot.info/wp-content/uploads/2025/01/1426.png",
      "time_baghdad": "17:00",
      "status": "NS",
      "status_text": "لم تبدأ بعد",
      "result_text": "0-0",
      "channel": "beIN Sports 6 HD",
      "commentator": "غير معروف",
      "competition": "إنجلترا, الدوري الإنجليزي",
      "_source": "yalla1shoot"
    },
    {
      "id": "المقاولونال-كهرباءالاسم-2025-09-27",
      "home": "المقاولون العرب",
      "away": "كهرباء الاسماعيلية",
      "home_logo": "https://www.yalla-shoot.info/wp-content/uploads/2025/08/8310.png",
      "away_logo": "https://www.yalla-shoot.info/wp-content/uploads/2025/08/19506.png",
      "time_baghdad": "17:00",
      "status": "NS",
      "status_text": "لم تبدأ بعد",
      "result_text": "0-0",
      "channel": "أون سبورت 2",
      "commentator": "غير معروف",
      "competition": "مصر, الدوري المصري",
      "_source": "yalla1shoot"
    },
    {
      "id": "زد-حرسالحدود-2025-09-27",
      "home": "زد",
      "away": "حرس الحدود",
      "home_logo": "https://www.yalla-shoot.info/wp-content/uploads/2025/01/1683.png",
      "away_logo": "https://www.yalla-shoot.info/wp-content/uploads/2025/01/149.png",
      "time_baghdad": "17:00",
      "status": "NS",
      "status_text": "لم تبدأ بعد",
      "result_text": "0-0",
      "channel": "أون سبورت 1",
      "commentator": "غير معروف",
      "competition": "مصر, الدوري المصري",
      "_source": "yalla1shoot"
    },
    {
      "id": "ليدزيونايتد-بورنموث-2025-09-27",
      "home": "ليدز يونايتد",
      "away": "بورنموث",
      "home_logo": "https://www.yalla-shoot.info/wp-content/uploads/2025/08/36.png",
      "away_logo": "https://www.yalla-shoot.info/wp-content/uploads/2025/01/1453.png",
      "time_baghdad": "17:00",
      "status": "NS",
      "status_text": "لم تبدأ بعد",
      "result_text": "0-0",
      "channel": "beIN Sports 5 HD",
      "commentator": "غير معروف",
      "competition": "إنجلترا, الدوري الإنجليزي",
      "_source": "yalla1shoot"
    },
    {
      "id": "أتلتيكومدري-ريالمدريد-2025-09-27",
      "home": "أتلتيكو مدريد",
      "away": "ريال مدريد",
      "home_logo": "https://www.yalla-shoot.info/wp-content/uploads/2025/06/134.png",
      "away_logo": "https://www.yalla-shoot.info/wp-content/uploads/2025/01/110.png",
      "time_baghdad": "17:15",
      "status": "NS",
      "status_text": "لم تبدأ بعد",
      "result_text": "0-0",
      "channel": "beIN SPORTS HD 1",
      "commentator": "غير معروف",
      "competition": "إسبانيا, الدوري الإسباني",
      "_source": "yalla1shoot"
    },
    {
      "id": "لوريان-موناكو-2025-09-27",
      "home": "لوريان",
      "away": "موناكو",
      "home_logo": "https://www.yalla-shoot.info/wp-content/uploads/2025/08/472-1.png",
      "away_logo": "https://www.yalla-shoot.info/wp-content/uploads/2025/01/210.png",
      "time_baghdad": "18:00",
      "status": "NS",
      "status_text": "لم تبدأ بعد",
      "result_text": "0-0",
      "channel": "beIN SPORTS HD 4",
      "commentator": "غير معروف",
      "competition": "فرنسا, الدوري الفرنسي",
      "_source": "yalla1shoot"
    },
    {
      "id": "حوريا-الهلال-2025-09-27",
      "home": "حوريا",
      "away": "الهلال",
      "home_logo": "https://www.yalla-shoot.info/wp-content/uploads/2025/09/10476.png",
      "away_logo": "https://www.yalla-shoot.info/wp-content/uploads/2025/01/269.png",
      "time_baghdad": "19:00",
      "status": "NS",
      "status_text": "لم تبدأ بعد",
      "result_text": "0-0",
      "channel": "غير معروف",
      "commentator": "غير معروف",
      "competition": "أفريقيا, دوري أبطال أفريقيا - تصفيات",
      "_source": "yalla1shoot"
    },
    {
      "id": "يوفنتوس-أتالانتا-2025-09-27",
      "home": "يوفنتوس",
      "away": "أتالانتا",
      "home_logo": "https://www.yalla-shoot.info/wp-content/uploads/2025/02/135.png",
      "away_logo": "https://www.yalla-shoot.info/wp-content/uploads/2025/01/128.png",
      "time_baghdad": "19:00",
      "status": "NS",
      "status_text": "لم تبدأ بعد",
      "result_text": "0-0",
      "channel": "Starzplay",
      "commentator": "غير معروف",
      "competition": "إيطاليا, الدوري الإيطالي",
      "_source": "yalla1shoot"
    },
    {
      "id": "ريالمايوركا-ألافيس-2025-09-27",
      "home": "ريال مايوركا",
      "away": "ألافيس",
      "home_logo": "https://www.yalla-shoot.info/wp-content/uploads/2025/01/121.png",
      "away_logo": "https://www.yalla-shoot.info/wp-content/uploads/2025/08/168.png",
      "time_baghdad": "19:30",
      "status": "NS",
      "status_text": "لم تبدأ بعد",
      "result_text": "0-0",
      "channel": "beIN Sports 3 HD",
      "commentator": "غير معروف",
      "competition": "إسبانيا, الدوري الإسباني",
      "_source": "yalla1shoot"
    },
    {
      "id": "نوتنجهامفور-سندرلاند-2025-09-27",
      "home": "نوتنجهام فورست",
      "away": "سندرلاند",
      "home_logo": "https://www.yalla-shoot.info/wp-content/uploads/2025/08/29.png",
      "away_logo": "https://www.yalla-shoot.info/wp-content/uploads/2025/08/117.png",
      "time_baghdad": "19:30",
      "status": "NS",
      "status_text": "لم تبدأ بعد",
      "result_text": "0-0",
      "channel": "beIN SPORTS HD 1",
      "commentator": "غير معروف",
      "competition": "إنجلترا, الدوري الإنجليزي",
      "_source": "yalla1shoot"
    },
    {
      "id": "الترجي-القواتالمسل-2025-09-27",
      "home": "الترجي",
      "away": "القوات المسلحة",
      "home_logo": "https://www.yalla-shoot.info/wp-content/uploads/2025/02/254.png",
      "away_logo": "https://www.yalla-shoot.info/wp-content/uploads/2025/09/90265.png",
      "time_baghdad": "20:00",
      "status": "NS",
      "status_text": "لم تبدأ بعد",
      "result_text": "0-0",
      "channel": "غير معروف",
      "commentator": "غير معروف",
      "competition": "أفريقيا, دوري أبطال أفريقيا - تصفيات",
      "_source": "yalla1shoot"
    },
    {
      "id": "بيراميدز-طلائعالجيش-2025-09-27",
      "home": "بيراميدز",
      "away": "طلائع الجيش",
      "home_logo": "https://www.yalla-shoot.info/wp-content/uploads/2025/01/1451.png",
      "away_logo": "https://www.yalla-shoot.info/wp-content/uploads/2025/01/304.png",
      "time_baghdad": "20:00",
      "status": "NS",
      "status_text": "لم تبدأ بعد",
      "result_text": "0-0",
      "channel": "أون سبورت 2",
      "commentator": "غير معروف",
      "competition": "مصر, الدوري المصري",
      "_source": "yalla1shoot"
    },
    {
      "id": "المصري-بتروجت-2025-09-27",
      "home": "المصري",
      "away": "بتروجت",
      "home_logo": "https://www.yalla-shoot.info/wp-content/uploads/2025/01/8.png",
      "away_logo": "https://www.yalla-shoot.info/wp-content/uploads/2025/01/653.png",
      "time_baghdad": "20:00",
      "status": "NS",
      "status_text": "لم تبدأ بعد",
      "result_text": "0-0",
      "channel": "أون سبورت 1",
      "commentator": "غير معروف",
      "competition": "مصر, الدوري المصري",
      "_source": "yalla1shoot"
    },
    {
      "id": "تولوز-نانت-2025-09-27",
      "home": "تولوز",
      "away": "نانت",
      "home_logo": "https://www.yalla-shoot.info/wp-content/uploads/2025/02/315.png",
      "away_logo": "https://www.yalla-shoot.info/wp-content/uploads/2025/02/244.png",
      "time_baghdad": "20:00",
      "status": "NS",
      "status_text": "لم تبدأ بعد",
      "result_text": "0-0",
      "channel": "beIN Sports 5 HD",
      "commentator": "غير معروف",
      "competition": "فرنسا, الدوري الفرنسي",
      "_source": "yalla1shoot"
    },
    {
      "id": "كالياري-إنترميلان-2025-09-27",
      "home": "كالياري",
      "away": "إنتر ميلان",
      "home_logo": "https://www.yalla-shoot.info/wp-content/uploads/2025/02/324.png",
      "away_logo": "https://www.yalla-shoot.info/wp-content/uploads/2025/06/224.png",
      "time_baghdad": "21:45",
      "status": "NS",
      "status_text": "لم تبدأ بعد",
      "result_text": "0-0",
      "channel": "Starzplay",
      "commentator": "غير معروف",
      "competition": "إيطاليا, الدوري الإيطالي",
      "_source": "yalla1shoot"
    },
    {
      "id": "الجيشالملكي-ريالديبانج-2025-09-27",
      "home": "الجيش الملكي",
      "away": "ريال دي بانجول",
      "home_logo": "https://www.yalla-shoot.info/wp-content/uploads/2025/01/440.png",
      "away_logo": "https://www.yalla-shoot.info/wp-content/uploads/2025/09/10471.png",
      "time_baghdad": "22:00",
      "status": "NS",
      "status_text": "لم تبدأ بعد",
      "result_text": "0-0",
      "channel": "غير معروف",
      "commentator": "غير معروف",
      "competition": "أفريقيا, دوري أبطال أفريقيا - تصفيات",
      "_source": "yalla1shoot"
    },
    {
      "id": "فياريال-أتلتيكبلباو-2025-09-27",
      "home": "فياريال",
      "away": "أتلتيك بلباو",
      "home_logo": "https://www.yalla-shoot.info/wp-content/uploads/2025/01/127.png",
      "away_logo": "https://www.yalla-shoot.info/wp-content/uploads/2025/08/144.png",
      "time_baghdad": "22:00",
      "status": "NS",
      "status_text": "لم تبدأ بعد",
      "result_text": "0-0",
      "channel": "beIN Sports 3 HD",
      "commentator": "غير معروف",
      "competition": "إسبانيا, الدوري الإسباني",
      "_source": "yalla1shoot"
    },
    {
      "id": "مولوديةالجز-فاسل-2025-09-27",
      "home": "مولودية الجزائر",
      "away": "فاسل",
      "home_logo": "https://www.yalla-shoot.info/wp-content/uploads/2025/09/8218.png",
      "away_logo": "https://www.yalla-shoot.info/wp-content/uploads/2025/09/84434.png",
      "time_baghdad": "22:00",
      "status": "NS",
      "status_text": "لم تبدأ بعد",
      "result_text": "0-0",
      "channel": "الجزائرية السادسة",
      "commentator": "غير معروف",
      "competition": "أفريقيا, دوري أبطال أفريقيا - تصفيات",
      "_source": "yalla1shoot"
    },
    {
      "id": "توتنهامهوتس-وولفرهامبتون-2025-09-27",
      "home": "توتنهام هوتسبر",
      "away": "وولفرهامبتون",
      "home_logo": "https://www.yalla-shoot.info/wp-content/uploads/2025/08/114.png",
      "away_logo": "https://www.yalla-shoot.info/wp-content/uploads/2025/08/15.png",
      "time_baghdad": "22:00",
      "status": "NS",
      "status_text": "لم تبدأ بعد",
      "result_text": "0-0",
      "channel": "Bein Sports HD2",
      "commentator": "غير معروف",
      "competition": "إنجلترا, الدوري الإنجليزي",
      "_source": "yalla1shoot"
    },
    {
      "id": "باريسسانجي-أوكسير-2025-09-27",
      "home": "باريس سان جيرمان",
      "away": "أوكسير",
      "home_logo": "https://www.yalla-shoot.info/wp-content/uploads/2025/02/237.png",
      "away_logo": "https://www.yalla-shoot.info/wp-content/uploads/2025/01/302.png",
      "time_baghdad": "22:05",
      "status": "NS",
      "status_text": "لم تبدأ بعد",
      "result_text": "0-0",
      "channel": "beIN SPORTS HD 1",
      "commentator": "غير معروف",
      "competition": "فرنسا, الدوري الفرنسي",
      "_source": "yalla1shoot"
    },
    {
      "id": "نهضةبركان-كارا-2025-09-27",
      "home": "نهضة بركان",
      "away": "كارا",
      "home_logo": "https://www.yalla-shoot.info/wp-content/uploads/2025/01/1529.png",
      "away_logo": "https://www.yalla-shoot.info/wp-content/uploads/2025/09/57634.png",
      "time_baghdad": "23:00",
      "status": "NS",
      "status_text": "لم تبدأ بعد",
      "result_text": "0-0",
      "channel": "غير معروف",
      "commentator": "غير معروف",
      "competition": "أفريقيا, دوري أبطال أفريقيا - تصفيات",
      "_source": "yalla1shoot"
    }
  ]
}